Metadata-Version: 2.1
Name: linkedin-queens-solver
Version: 0.0.2
Summary: lib to solve the linkedin daily challenge `Queens`
Home-page: https://github.com/Utkarsh-Deshmukh/Linkedin_Queens_challenge
Author: utkarsh-deshmukh
Author-email: utkarsh.deshmukh@gmail.com
License: MIT License
Download-URL: https://github.com/Utkarsh-Deshmukh/Linkedin_Queens_challenge/archive/refs/heads/main.zip
Keywords: Linkedin Daily challenge Queens
Platform: UNKNOWN
Classifier: Programming Language :: Python :: 3
Classifier: License :: OSI Approved :: BSD License
Classifier: Operating System :: OS Independent
License-File: LICENSE
